Kavach/__init__.py
Kavach/gradio_app.py
Kavach/utils.py
Kavach/data/logo.png
tests/__init__.py
tests/test_utils.py
Kavach-0.3.dist-info/METADATA
Kavach-0.3.dist-info/WHEEL
Kavach-0.3.dist-info/entry_points.txt
Kavach-0.3.dist-info/top_level.txt
Kavach-0.3.dist-info/RECORD
