Metadata-Version: 2.1
Name: Kavach
Version: 0.3
Requires-Python: >=3.7
Requires-Dist: transformers
Requires-Dist: torch
Requires-Dist: gradio
Requires-Dist: pandas
